openbci/__init__.py
openbci/_version.txt
openbci/acquisition/__init__.py
openbci/acquisition/cyton.py
openbci/acquisition/cyton_bin_parser.py
openbci/database/__init__.py
openbci/database/raw2bin.py
openbci/database/sample_8ch_bin0.txt
openbci/database/sample_8ch_bin1.txt
openbci/database/sample_8ch_bin2.txt
openbci/database/sample_8ch_raw0.txt
openbci/database/sample_8ch_raw1.txt
openbci/database/sample_8ch_raw2.txt
openbci/handlers/__init__.py
openbci/handlers/eegframe.py
openbci/preprocess/__init__.py
openbci/preprocess/eeg_connectivity.py
openbci/preprocess/eeg_features.py
openbci/preprocess/eeg_filters.py
openbci/preprocess37/__init__.py
openbci/preprocess37/eeg_connectivity.py
openbci/preprocess37/eeg_features.py
openbci/preprocess37/eeg_filters.py
openbci/preprocess38/__init__.py
openbci/preprocess38/eeg_connectivity.py
openbci/preprocess38/eeg_features.py
openbci/preprocess38/eeg_filters.py
openbci/stream/__init__.py
openbci/stream/ws/__init__.py
openbci/stream/ws/app.py
openbci/stream/ws/base_server.py
openbci/stream/ws/client.py
openbci/stream/ws/server.py
openbci/stream/ws/html/home.html
openbci/stream/ws/static/bootstrap-4.3.1-dist/css/bootstrap-grid.css
openbci/stream/ws/static/bootstrap-4.3.1-dist/css/bootstrap-grid.css.map
openbci/stream/ws/static/bootstrap-4.3.1-dist/css/bootstrap-grid.min.css
openbci/stream/ws/static/bootstrap-4.3.1-dist/css/bootstrap-grid.min.css.map
openbci/stream/ws/static/bootstrap-4.3.1-dist/css/bootstrap-reboot.css
openbci/stream/ws/static/bootstrap-4.3.1-dist/css/bootstrap-reboot.css.map
openbci/stream/ws/static/bootstrap-4.3.1-dist/css/bootstrap-reboot.min.css
openbci/stream/ws/static/bootstrap-4.3.1-dist/css/bootstrap-reboot.min.css.map
openbci/stream/ws/static/bootstrap-4.3.1-dist/css/bootstrap.css
openbci/stream/ws/static/bootstrap-4.3.1-dist/css/bootstrap.css.map
openbci/stream/ws/static/bootstrap-4.3.1-dist/css/bootstrap.min.css
openbci/stream/ws/static/bootstrap-4.3.1-dist/css/bootstrap.min.css.map
openbci-0.2.3.dist-info/LICENSE.txt
openbci-0.2.3.dist-info/METADATA
openbci-0.2.3.dist-info/WHEEL
openbci-0.2.3.dist-info/top_level.txt
openbci-0.2.3.dist-info/RECORD
