Metadata-Version: 2.1
Name: openbci
Version: 0.2.3
Summary: Hight level Python module for OpenBCI hardware by GCPDS.
Home-page: UNKNOWN
Author: Yeison Cardona
Author-email: yeisoneng@gmail.com
Maintainer: Yeison Cardona
Maintainer-email: yeisoneng@gmail.com
License: Simplified BSD License
Download-URL: https://bitbucket.org/gcpds/openbci/downloads/
Platform: UNKNOWN
Classifier: Development Status :: 4 - Beta
Classifier: Intended Audience :: Developers
Classifier: Intended Audience :: Education
Classifier: Intended Audience :: Healthcare Industry
Classifier: Intended Audience :: Science/Research
Classifier: License :: OSI Approved :: BSD License
Classifier: Programming Language :: Python :: 3.7
Classifier: Programming Language :: Python :: 3.8
Classifier: Topic :: Scientific/Engineering
Classifier: Topic :: Scientific/Engineering :: Artificial Intelligence
Classifier: Topic :: Scientific/Engineering :: Human Machine Interfaces
Classifier: Topic :: Scientific/Engineering :: Medical Science Apps.
Classifier: Topic :: Software Development :: Embedded Systems
Classifier: Topic :: Software Development :: Libraries
Classifier: Topic :: Software Development :: Libraries :: Application Frameworks
Classifier: Topic :: Software Development :: Libraries :: Python Modules
Classifier: Topic :: System :: Hardware :: Hardware Drivers
Requires-Python: >=3.6
Requires-Dist: pyserial
Requires-Dist: scipy (>=1.3.1)
Requires-Dist: numpy
Requires-Dist: psutil
Requires-Dist: mne
Requires-Dist: requests
Requires-Dist: tornado
Provides-Extra: utils
Requires-Dist: systemd-service ; extra == 'utils'
Requires-Dist: netifaces ; extra == 'utils'
Requires-Dist: python-nmap ; extra == 'utils'
Requires-Dist: quickapi ; extra == 'utils'
